<?xml version="1.0"?>

<PropertyList>


 <!-- =============================================================== -->
 <!-- ENGINE OUTSIDE:                                                 -->
 <!-- =============================================================== -->

		<engine>
			<name>RR left engine</name>
			<path>Aircraft/A330-200/Sounds/res/RR/jet.wav</path>
			<mode>looped</mode>
			<condition>
				<not>
					<property>controls/engines/engine[0]/cutoff</property>
				</not>
				<not>
					<property>sim/current-view/internal</property>
				</not>
				<equals>
					<property>sim/aero</property>
					<value>A330-243</value>
				</equals>
			</condition>
			<volume>
				<property>engines/engine[0]/thrust_lb</property>
				<factor>0.000028571</factor>
				<min>0.0</min>
				<max>1</max>
			</volume>
			<position>
				<x>15</x>
				<y>-5.7</y>
				<z>-1.1</z>
			</position>
			<reference-dist>50.0</reference-dist>
			<max-dist>500.0</max-dist>
		</engine>

		<engine>
			<name>RR right engine</name>
			<path>Aircraft/A330-200/Sounds/res/RR/jet.wav</path>
			<mode>looped</mode>
			<condition>
				<not>
					<property>controls/engines/engine[0]/cutoff</property>
				</not>
				<not>
					<property>sim/current-view/internal</property>
				</not>
				<equals>
					<property>sim/aero</property>
					<value>A330-243</value>
				</equals>
			</condition>
			<volume>
				<property>engines/engine[0]/thrust_lb</property>
				<factor>0.000028571</factor>
				<min>0.0</min>
				<max>1</max>
			</volume>
			<position>
				<x>15</x>
				<y>5.7</y>
				<z>-1.1</z>
			</position>
			<reference-dist>50.0</reference-dist>
			<max-dist>1000.0</max-dist>
		</engine>

		<engine>
			<name>RR left n1_2</name>
			<path>Aircraft/A330-200/Sounds/res/RR/turbine_NL1.wav</path>
			<mode>looped</mode>
			<condition>
				<greater-than>
					<property>engines/engine[0]/n1</property>
					<value>2</value>
				</greater-than>
				<not>
					<property>sim/current-view/internal</property>
				</not>
				<equals>
					<property>sim/aero</property>
					<value>A330-243</value>
				</equals>
			</condition>
			<pitch>
				<property>/engines/engine[0]/n1</property>
				<offset>0</offset>
				<factor>0.02</factor>
				<min>0.0</min>
				<max>2.1</max> <!-- War auf 2.0 -->
			</pitch>
			<volume>
				<property>engines/engine[0]/n1</property>
				<factor>0.01</factor>
				<min>0</min>
				<max>0.9</max> <!-- War auf 0.6 -->
			</volume>
			<position>
				<x>15</x>
				<y>-5.7</y>
				<z>-1.1</z>
			</position>
			<reference-dist>50.0</reference-dist>
			<max-dist>1000.0</max-dist>
		</engine>
		<engine>
			<name>RR right n1_2</name>
			<path>Aircraft/A330-200/Sounds/res/RR/turbine_NL1.wav</path>
			<mode>looped</mode>
			<condition>
				<greater-than>
					<property>engines/engine[1]/n1</property>
					<value>2</value>
				</greater-than>
				<not>
					<property>sim/current-view/internal</property>
				</not>
				<equals>
					<property>sim/aero</property>
					<value>A330-243</value>
				</equals>
			</condition>
			<pitch>
				<property>/engines/engine[1]/n1</property>
				<offset>0</offset>
				<factor>0.02</factor>
				<min>0.0</min>
				<max>2.1</max>
			</pitch>
			<volume>
				<property>engines/engine[1]/n1</property>
				<factor>0.01</factor>
				<min>0</min>
				<max>0.9</max>
			</volume>
			<position>
				<x>15</x>
				<y>5.7</y>
				<z>-1.1</z>
			</position>
			<reference-dist>50.0</reference-dist>
			<max-dist>1000.0</max-dist>
		</engine>
		<engine>
			<name>RR left whine</name>
			<path>Aircraft/A330-200/Sounds/res/RR/whine_NL1.wav</path>
			<mode>looped</mode>
			<condition>
				<greater-than>
					<property>engines/engine[0]/n1</property>
					<value>42</value>
				</greater-than>
				<not>
					<property>sim/current-view/internal</property>
				</not>
				<equals>
					<property>sim/aero</property>
					<value>A330-243</value>
				</equals>
			</condition>
			<pitch>
				<property>/engines/engine[0]/n1</property>
				<offset>-0.5</offset>
				<factor>0.02</factor>
				<min>0.0</min>
				<max>3.2</max> <!-- War auf 2.0 -->
			</pitch>
			<volume>
				<property>engines/engine[0]/n1</property>
				<factor>0.01</factor>
				<min>0</min>
				<max>0.8</max> <!-- War auf 0.6 -->
			</volume>
			<position>
				<x>15</x>
				<y>-5.7</y>
				<z>-1.1</z>
			</position>
			<reference-dist>50.0</reference-dist>
			<max-dist>1000.0</max-dist>
		</engine>
		<engine>
			<name>RR right whine</name>
			<path>Aircraft/A330-200/Sounds/res/RR/whine_NL1.wav</path>
			<mode>looped</mode>
			<condition>
				<greater-than>
					<property>engines/engine[1]/n1</property>
					<value>42</value>
				</greater-than>
				<not>
					<property>sim/current-view/internal</property>
				</not>
				<equals>
					<property>sim/aero</property>
					<value>A330-243</value>
				</equals>
			</condition>
			<pitch>
				<property>/engines/engine[1]/n1</property>
				<offset>-0.5</offset>
				<factor>0.02</factor>
				<min>0.0</min>
				<max>3.2</max>
			</pitch>
			<volume>
				<property>engines/engine[1]/n1</property>
				<factor>0.01</factor>
				<min>0</min>
				<max>0.8</max>
			</volume>
			<position>
				<x>15</x>
				<y>5.7</y>
				<z>-1.1</z>
			</position>
			<reference-dist>50.0</reference-dist>
			<max-dist>1000.0</max-dist>
		</engine>

 <!-- =============================================================== -->
 <!-- ENGINE INSIDE:                                                  -->
 <!-- =============================================================== -->

		<engine>
			<name>RR inside left engine</name>
			<path>Aircraft/A330-200/Sounds/res/RR/jet.wav</path>
			<mode>looped</mode>
			<condition>
				<not>
					<property>controls/engines/engine[0]/cutoff</property>
				</not>
				<property>sim/current-view/internal</property>
				<equals>
					<property>sim/aero</property>
					<value>A330-243</value>
				</equals>
			</condition>
			<volume>
				<property>engines/engine[0]/thrust_lb</property>
				<factor>0.000021428</factor>
				<min>0.0</min>
				<max>1</max>
			</volume>


			<position>
				<x>15</x>
				<y>-5.7</y>
				<z>-1.1</z>
			</position>
			<reference-dist>1.0</reference-dist>
			<max-dist>50.0</max-dist>
		</engine>

		<engine>
			<name>RR inside right engine</name>
			<path>Aircraft/A330-200/Sounds/res/RR/jet.wav</path>
			<mode>looped</mode>
			<condition>
				<not>
					<property>controls/engines/engine[0]/cutoff</property>
				</not>
				<property>sim/current-view/internal</property>
				<equals>
					<property>sim/aero</property>
					<value>A330-243</value>
				</equals>
			</condition>
			<volume>
				<property>engines/engine[0]/thrust_lb</property>
				<factor>0.000021428</factor>
				<min>0.0</min>
				<max>1</max>
			</volume>

			<position>
				<x>15</x>
				<y>5.7</y>
				<z>-1.1</z>
			</position>
			<reference-dist>1.0</reference-dist>
			<max-dist>50.0</max-dist>
		</engine>

		<engine>
			<name>RR inside left n1_2</name>
			<path>Aircraft/A330-200/Sounds/res/RR/turbine_NL1.wav</path>
			<mode>looped</mode>
			<condition>
				<greater-than>
					<property>engines/engine[0]/n1</property>
					<value>2</value>
				</greater-than>
				<property>sim/current-view/internal</property>
				<equals>
					<property>sim/aero</property>
					<value>A330-243</value>
				</equals>
			</condition>
			<pitch>
				<property>/engines/engine[0]/n1</property>
				<offset>0</offset>
				<factor>0.02</factor>
				<min>0.0</min>
				<max>2.1</max>
			</pitch>
			<volume>
				<property>engines/engine[0]/n1</property>
				<factor>0.0025</factor>
				<min>0</min>
				<max>0.9</max>
			</volume>

			<position>
				<x>15</x>
				<y>-5.7</y>
				<z>-1.1</z>
			</position>
			<reference-dist>25.0</reference-dist>
			<max-dist>50.0</max-dist>
		</engine>
		<engine>
			<name>RR inside right n1_2</name>
			<path>Aircraft/A330-200/Sounds/res/RR/turbine_NL1.wav</path>
			<mode>looped</mode>
			<condition>
				<greater-than>
					<property>engines/engine[1]/n1</property>
					<value>2</value>
				</greater-than>
				<property>sim/current-view/internal</property>
				<equals>
					<property>sim/aero</property>
					<value>A330-243</value>
				</equals>
			</condition>
			<pitch>
				<property>/engines/engine[1]/n1</property>
				<offset>0</offset>
				<factor>0.02</factor>
				<min>0.0</min>
				<max>2.0</max>
			</pitch>
			<volume>
				<property>engines/engine[1]/n1</property>
				<factor>0.0025</factor>
				<min>0</min>
				<max>0.9</max>
			</volume>

			<position>
				<x>15</x>
				<y>5.7</y>
				<z>-1.1</z>
			</position>
			<reference-dist>1.0</reference-dist>
			<max-dist>50.0</max-dist>
		</engine>
		<engine>
			<name>RR inside left whine</name>
			<path>Aircraft/A330-200/Sounds/res/RR/whine_NL1.wav</path>
			<mode>looped</mode>
			<condition>
				<greater-than>
					<property>engines/engine[0]/n1</property>
					<value>42</value>
				</greater-than>
				<property>sim/current-view/internal</property>
				<equals>
					<property>sim/aero</property>
					<value>A330-243</value>
				</equals>
			</condition>
			<pitch>
				<property>/engines/engine[0]/n1</property>
				<offset>-0.5</offset>
				<factor>0.02</factor>
				<min>0.0</min>
				<max>3.2</max>
			</pitch>
			<volume>
				<property>engines/engine[0]/n1</property>
				<factor>0.0025</factor>
				<min>0</min>
				<max>0.8</max>
			</volume>

			<position>
				<x>15</x>
				<y>-5.7</y>
				<z>-1.1</z>
			</position>
			<reference-dist>25.0</reference-dist>
			<max-dist>50.0</max-dist>
		</engine>
		<engine>
			<name>RR inside right whine</name>
			<path>Aircraft/A330-200/Sounds/res/RR/whine_NL1.wav</path>
			<mode>looped</mode>
			<condition>
				<greater-than>
					<property>engines/engine[1]/n1</property>
					<value>42</value>
				</greater-than>
				<property>sim/current-view/internal</property>
				<equals>
					<property>sim/aero</property>
					<value>A330-243</value>
				</equals>
			</condition>
			<pitch>
				<property>/engines/engine[1]/n1</property>
				<offset>-0.5</offset>
				<factor>0.02</factor>
				<min>0.0</min>
				<max>3.2</max>
			</pitch>
			<volume>
				<property>engines/engine[1]/n1</property>
				<factor>0.0025</factor>
				<min>0</min>
				<max>0.8</max>
			</volume>

			<position>
				<x>15</x>
				<y>5.7</y>
				<z>-1.1</z>
			</position>
			<reference-dist>1.0</reference-dist>
			<max-dist>50.0</max-dist>
		</engine>

</PropertyList>
